{
	"installed":{
		"auth_provider_x509_cert_url":"https://www.googleapis.com/oauth2/v1/certs",
		"auth_uri":"https://accounts.google.com/o/oauth2/auth",
		"client_id":"991805940531-405a0p01fg43d7vnnlicaknjrdqgicjh.apps.googleusercontent.com",
		"client_secret":"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",
		"project_id":"amri-dev",
		"redirect_uris":[
			"http://localhost"
		],
		"token_uri":"https://oauth2.googleapis.com/token"
	},
	"installed":{
		"auth_provider_x509_cert_url":"https://www.googleapis.com/oauth2/v1/certs",
		"auth_uri":"https://accounts.google.com/o/oauth2/auth",
		"client_id":"991805940531-405a0p01fg43d7vnnlicaknjrdqgicjh.apps.googleusercontent.com",
		"client_secret":"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",
		"project_id":"amri-dev",
		"redirect_uris":[
			"http://localhost"
		],
		"token_uri":"https://oauth2.googleapis.com/token"
	}
}
